basicsums/__init__.py
basicsums/basic_sums.py
basicsums/conductivity.py
basicsums/eisenstein.py
basicsums/multi_indexes.py
basicsums/preparation.py
basicsums/show_disks.py
basicsums/weierstrass.py
basicsums/examples/__init__.py
basicsums/examples/base_examples.py
basicsums/examples/data/example01.npz
basicsums/examples/data/example02.npz
basicsums/examples/data/example03hex.npz
basicsums/examples/data/example03hex_e44.npz
basicsums/examples/data/example03sqr.npz
basicsums/examples/data/example03sqr_e44.npz
basicsums/examples/data/example04rNorm.npz
basicsums/examples/data/example04rUnif.npz
basicsums/tests/__init__.py
basicsums/tests/basic_sums.doctest
basicsums/tests/conductivity.doctest
basicsums/tests/test.py
basicsums/tests/weierstrass.doctest
basicsums/tests/weierstrass.doctest.data/diffs_hex.dat
basicsums/tests/weierstrass.doctest.data/diffs_sqr.dat
basicsums/tests/weierstrass.doctest.data/wp_hex_math11.dat
basicsums/tests/weierstrass.doctest.data/wp_sqr_math11.dat
basicsums/tests/weierstrass.doctest.data/wpp_hex_math11.dat
basicsums/tests/weierstrass.doctest.data/wpp_sqr_math11.dat
basicsums-1.0.2.dist-info/LICENSE.txt
basicsums-1.0.2.dist-info/METADATA
basicsums-1.0.2.dist-info/WHEEL
basicsums-1.0.2.dist-info/top_level.txt
basicsums-1.0.2.dist-info/RECORD
