Metadata-Version: 2.1
Name: basicsums
Version: 1.0.2
Summary: A package for computing structural sums and the effective conductivity of random composites.
Home-page: http://basicsums.bitbucket.io/
Author: Wojciech Nawalaniec
Author-email: wnawalaniec@gmail.com
License: LICENSE.txt
Platform: UNKNOWN
Classifier: Programming Language :: Python :: 3
Requires-Dist: numpy (>=1.14.0)
Requires-Dist: matplotlib (>=2.1.2)
Requires-Dist: sympy (>=1.1.1)
